<?xml version="1.0" encoding="UTF-8"?>
<specification xmlns:xsi="http://www.w3.org/2001/XMLSchema-instance" ciUrl="https://build.fhir.org/ig/HL7/CDA-ccda-2.1-sd" defaultVersion="current" defaultWorkgroup="sd" url="http://hl7.org/cda/us/ccda">
<version code="current" url="https://build.fhir.org/ig/HL7/CDA-ccda-2.1-sd"/>
<version code="2.1.0-draft1" url="http://hl7.org/cda/stds/ccda/draft1"/>
<artifactPageExtension value="-definitions"/>
<artifactPageExtension value="-examples"/>
<artifactPageExtension value="-mappings"/>
<artifact id="StructureDefinition/2.16.840.1.113883.10.20.22.2.43" key="StructureDefinition-2.16.840.1.113883.10.20.22.2.43" name="Admission Diagnosis Section"/>
<artifact id="Binary/admission-diagnosis-section-v3-example" key="Binary-admission-diagnosis-section-v3-example" name="Admission Diagnosis Section Example"/>
<artifact id="StructureDefinition/2.16.840.1.113883.10.20.22.4.36" key="StructureDefinition-2.16.840.1.113883.10.20.22.4.36" name="Admission Medication"/>
<artifact id="Binary/admission-medication-v2-example" key="Binary-admission-medication-v2-example" name="Admission Medication example"/>
<artifact id="StructureDefinition/2.16.840.1.113883.10.20.22.2.44" key="StructureDefinition-2.16.840.1.113883.10.20.22.2.44" name="Admission Medications Section (entries optional)"/>
<artifact id="StructureDefinition/2.16.840.1.113883.10.20.22.4.48" key="StructureDefinition-2.16.840.1.113883.10.20.22.4.48" name="Advance Directive Observation"/>
<artifact id="Binary/advance-directive-observation-v3-example" key="Binary-advance-directive-observation-v3-example" name="Advance Directive Observation Example"/>
<artifact id="StructureDefinition/2.16.840.1.113883.10.20.22.4.108" key="StructureDefinition-2.16.840.1.113883.10.20.22.4.108" name="Advance Directive Organizer"/>
<artifact id="Binary/advance-directive-organizer-v2-example" key="Binary-advance-directive-organizer-v2-example" name="Advance Directive Organizer Example"/>
<artifact id="StructureDefinition/2.16.840.1.113883.10.20.22.2.21.1" key="StructureDefinition-2.16.840.1.113883.10.20.22.2.21.1" name="Advance Directives Section"/>
<artifact id="Binary/advance-directives-section-v3-example" key="Binary-advance-directives-section-v3-example" name="Advance Directives Section Example"/>
<artifact id="StructureDefinition/2.16.840.1.113883.10.20.22.4.31" key="StructureDefinition-2.16.840.1.113883.10.20.22.4.31" name="Age Observation"/>
<artifact id="Binary/age-observation-example" key="Binary-age-observation-example" name="Age Observation Example"/>
<artifact id="StructureDefinition/2.16.840.1.113883.10.20.22.2.6.1" key="StructureDefinition-2.16.840.1.113883.10.20.22.2.6.1" name="Allergies and Intolerances Section"/>
<artifact id="Binary/allergies-and-intolerances-section-v3-example" key="Binary-allergies-and-intolerances-section-v3-example" name="Allergies and Intolerances Section Example"/>
<artifact id="StructureDefinition/2.16.840.1.113883.10.20.22.4.7" key="StructureDefinition-2.16.840.1.113883.10.20.22.4.7" name="Allergy - Intolerance Observation"/>
<artifact id="StructureDefinition/2.16.840.1.113883.10.20.22.4.30" key="StructureDefinition-2.16.840.1.113883.10.20.22.4.30" name="Allergy Concern Act"/>
<artifact id="Binary/allergy-concern-act-v3-example" key="Binary-allergy-concern-act-v3-example" name="Allergy Concern Act Example"/>
<artifact id="Binary/allergy-intolerance-observation-v2-example" key="Binary-allergy-intolerance-observation-v2-example" name="Allergy Intolerance Observation Example"/>
<artifact id="StructureDefinition/2.16.840.1.113883.10.20.22.4.28" key="StructureDefinition-2.16.840.1.113883.10.20.22.4.28" name="Allergy Status Observation"/>
<artifact id="StructureDefinition/2.16.840.1.113883.10.20.22.2.25" key="StructureDefinition-2.16.840.1.113883.10.20.22.2.25" name="Anesthesia Section"/>
<artifact id="Binary/anesthesia-section-v2-example" key="Binary-anesthesia-section-v2-example" name="Anesthesia Section Example"/>
<artifact id="StructureDefinition/2.16.840.1.113883.10.20.22.4.69" key="StructureDefinition-2.16.840.1.113883.10.20.22.4.69" name="Assessment Scale Observation"/>
<artifact id="Binary/assessment-scale-observation-example" key="Binary-assessment-scale-observation-example" name="Assessment Scale Observation Example"/>
<artifact id="StructureDefinition/2.16.840.1.113883.10.20.22.4.86" key="StructureDefinition-2.16.840.1.113883.10.20.22.4.86" name="Assessment Scale Supporting Observation"/>
<artifact id="Binary/assessment-scale-supporting-observation-example" key="Binary-assessment-scale-supporting-observation-example" name="Assessment Scale Supporting Observation Example"/>
<artifact id="StructureDefinition/2.16.840.1.113883.10.20.22.2.8" key="StructureDefinition-2.16.840.1.113883.10.20.22.2.8" name="Assessment Section"/>
<artifact id="Binary/assessment-section-example" key="Binary-assessment-section-example" name="Assessment Section Example"/>
<artifact id="StructureDefinition/2.16.840.1.113883.10.20.22.2.9" key="StructureDefinition-2.16.840.1.113883.10.20.22.2.9" name="Assessment and Plan Section"/>
<artifact id="Binary/assessment-and-plan-section-v2-example" key="Binary-assessment-and-plan-section-v2-example" name="Assessment and Plan Section Example"/>
<artifact id="StructureDefinition/2.16.840.1.113883.10.20.22.4.119" key="StructureDefinition-2.16.840.1.113883.10.20.22.4.119" name="Author Participation"/>
<artifact id="Binary/new-author-participant-example" key="Binary-new-author-participant-example" name="Author Participation Example"/>
<artifact id="StructureDefinition/2.16.840.1.113883.10.20.1.19" key="StructureDefinition-2.16.840.1.113883.10.20.1.19" name="Authorization Activity"/>
<artifact id="Binary/authorization-activity-example" key="Binary-authorization-activity-example" name="Authorization Activity Example"/>
<artifact id="StructureDefinition/2.16.840.1.113883.10.20.22.4.504" key="StructureDefinition-2.16.840.1.113883.10.20.22.4.504" name="Basic Industry Observation"/>
<artifact id="StructureDefinition/2.16.840.1.113883.10.20.22.4.503" key="StructureDefinition-2.16.840.1.113883.10.20.22.4.503" name="Basic Occupation Observation"/>
<artifact id="StructureDefinition/2.16.840.1.113883.10.20.22.4.200" key="StructureDefinition-2.16.840.1.113883.10.20.22.4.200" name="Birth Sex Observation"/>
<artifact id="StructureDefinition/2.16.840.1.113883.10.20.22.4.301" key="StructureDefinition-2.16.840.1.113883.10.20.22.4.301" name="Brand Name Observation"/>
<artifact id="StructureDefinition/2.16.840.1.113883.10.20.22.1.15" key="StructureDefinition-2.16.840.1.113883.10.20.22.1.15" name="Care Plan"/>
<artifact id="Binary/care-plan-caregiver-participant-example" key="Binary-care-plan-caregiver-participant-example" name="Care Plan Caregiver participant Example"/>
<artifact id="Binary/care-plan-patient-authenticator-example" key="Binary-care-plan-patient-authenticator-example" name="Care Plan Patient authenticator Example"/>
<artifact id="Binary/care-plan-review-example" key="Binary-care-plan-review-example" name="Care Plan Review Example"/>
<artifact id="Binary/care-plan-performer-example" key="Binary-care-plan-performer-example" name="Care Plan performer Example"/>
<artifact id="Binary/care-plan-relateddocument-example" key="Binary-care-plan-relateddocument-example" name="Care Plan relatedDocument Example"/>
<artifact id="StructureDefinition/2.16.840.1.113883.10.20.22.4.500.1" key="StructureDefinition-2.16.840.1.113883.10.20.22.4.500.1" name="Care Team Member Act"/>
<artifact id="StructureDefinition/2.16.840.1.113883.10.20.22.4.500.3" key="StructureDefinition-2.16.840.1.113883.10.20.22.4.500.3" name="Care Team Member Schedule Observation"/>
<artifact id="StructureDefinition/2.16.840.1.113883.10.20.22.4.500" key="StructureDefinition-2.16.840.1.113883.10.20.22.4.500" name="Care Team Organizer"/>
<artifact id="StructureDefinition/2.16.840.1.113883.10.20.22.4.500.2" key="StructureDefinition-2.16.840.1.113883.10.20.22.4.500.2" name="Care Team Type Observation"/>
<artifact id="StructureDefinition/2.16.840.1.113883.10.20.22.2.500" key="StructureDefinition-2.16.840.1.113883.10.20.22.2.500" name="Care Teams Section"/>
<artifact id="StructureDefinition/2.16.840.1.113883.10.20.22.4.72" key="StructureDefinition-2.16.840.1.113883.10.20.22.4.72" name="Caregiver Characteristics"/>
<artifact id="Binary/caregiver-characteristics-example" key="Binary-caregiver-characteristics-example" name="Caregiver Characteristics Example"/>
<artifact id="StructureDefinition/2.16.840.1.113883.10.20.22.4.302" key="StructureDefinition-2.16.840.1.113883.10.20.22.4.302" name="Catalog Number Observation"/>
<artifact id="StructureDefinition/2.16.840.1.113883.10.20.22.4.109" key="StructureDefinition-2.16.840.1.113883.10.20.22.4.109" name="Characteristics of Home Environment"/>
<artifact id="Binary/characteristics-of-home-environment-example" key="Binary-characteristics-of-home-environment-example" name="Characteristics of Home Environment Example"/>
<artifact id="StructureDefinition/1.3.6.1.4.1.19376.1.5.3.1.1.13.2.1" key="StructureDefinition-1.3.6.1.4.1.19376.1.5.3.1.1.13.2.1" name="Chief Complaint Section"/>
<artifact id="Binary/chief-complaint-section-example" key="Binary-chief-complaint-section-example" name="Chief Complaint Section Example"/>
<artifact id="StructureDefinition/2.16.840.1.113883.10.20.22.2.13" key="StructureDefinition-2.16.840.1.113883.10.20.22.2.13" name="Chief Complaint and Reason for Visit Section"/>
<artifact id="Binary/chief-complaint-and-reason-for-visit-section-example" key="Binary-chief-complaint-and-reason-for-visit-section-example" name="Chief Complaint and Reason for Visit Section Example"/>
<artifact id="StructureDefinition/2.16.840.1.113883.10.20.22.4.73" key="StructureDefinition-2.16.840.1.113883.10.20.22.4.73" name="Cognitive Status Problem Observation (DEPRECATED)"/>
<artifact id="StructureDefinition/2.16.840.1.113883.10.20.22.4.64" key="StructureDefinition-2.16.840.1.113883.10.20.22.4.64" name="Comment Activity"/>
<artifact id="Binary/comment-activity-example" key="Binary-comment-activity-example" name="Comment Activity Example"/>
<artifact id="StructureDefinition/2.16.840.1.113883.10.20.22.4.303" key="StructureDefinition-2.16.840.1.113883.10.20.22.4.303" name="Company Name Observation"/>
<artifact id="StructureDefinition/2.16.840.1.113883.10.20.22.2.37" key="StructureDefinition-2.16.840.1.113883.10.20.22.2.37" name="Complications Section"/>
<artifact id="Binary/complications-section-v3-example" key="Binary-complications-section-v3-example" name="Complications Section Example"/>
<artifact id="StructureDefinition/2.16.840.1.113883.10.20.22.1.4" key="StructureDefinition-2.16.840.1.113883.10.20.22.1.4" name="Consultation Note"/>
<artifact id="Binary/consultation-note-callback-participant-example" key="Binary-consultation-note-callback-participant-example" name="Consultation Note Callback participant Example"/>
<artifact id="Binary/consultation-note-v2-infulfillmentof-example" key="Binary-consultation-note-v2-infulfillmentof-example" name="Consultation Note inFulfillmentOf Example"/>
<artifact id="Binary/consultation-note-structuredbody-example" key="Binary-consultation-note-structuredbody-example" name="Consultation Note structuredBody"/>
<artifact id="Binary/ccd-v2-author-example" key="Binary-ccd-v2-author-example" name="Continuity Of Care Document Author Example"/>
<artifact id="Binary/ccd-v2-performer-example" key="Binary-ccd-v2-performer-example" name="Continuity Of Care Document Performer"/>
<artifact id="Binary/ccd-v2-serviceevent-example" key="Binary-ccd-v2-serviceevent-example" name="Continuity Of Care Document serviceEvent Example"/>
<artifact id="StructureDefinition/2.16.840.1.113883.10.20.22.1.2" key="StructureDefinition-2.16.840.1.113883.10.20.22.1.2" name="Continuity of Care Document (CCD)"/>
<artifact id="StructureDefinition/2.16.840.1.113883.10.20.22.2.64" key="StructureDefinition-2.16.840.1.113883.10.20.22.2.64" name="Course of Care Section"/>
<artifact id="Binary/course-of-care-section-example" key="Binary-course-of-care-section-example" name="Course of Care Section Example"/>
<artifact id="StructureDefinition/2.16.840.1.113883.10.20.22.4.60" key="StructureDefinition-2.16.840.1.113883.10.20.22.4.60" name="Coverage Activity"/>
<artifact id="Binary/coverage-activity-v3-example" key="Binary-coverage-activity-v3-example" name="Coverage Activity Example"/>
<artifact id="StructureDefinition/2.16.840.1.113883.10.20.22.4.145" key="StructureDefinition-2.16.840.1.113883.10.20.22.4.145" name="Criticality Observation"/>
<artifact id="Binary/criticality-observation-example" key="Binary-criticality-observation-example" name="Criticality Observation Example"/>
<artifact id="StructureDefinition/2.16.840.1.113883.10.20.22.4.111" key="StructureDefinition-2.16.840.1.113883.10.20.22.4.111" name="Cultural and Religious Observation"/>
<artifact id="Binary/cultural-and-religious-observation-example" key="Binary-cultural-and-religious-observation-example" name="Cultural and Religious Observation Example"/>
<artifact id="StructureDefinition/2.16.840.1.113883.10.20.22.4.502" key="StructureDefinition-2.16.840.1.113883.10.20.22.4.502" name="Date of Diagnosis Act"/>
<artifact id="StructureDefinition/2.16.840.1.113883.10.20.22.4.79" key="StructureDefinition-2.16.840.1.113883.10.20.22.4.79" name="Deceased Observation"/>
<artifact id="Binary/deceased-observation-v3-example" key="Binary-deceased-observation-v3-example" name="Deceased Observation Example"/>
<artifact id="StructureDefinition/2.16.840.1.113883.10.20.22.4.304" key="StructureDefinition-2.16.840.1.113883.10.20.22.4.304" name="Device Identifier Observation"/>
<artifact id="Binary/diagnosis-reference-example" key="Binary-diagnosis-reference-example" name="Diagnosis Reference Example"/>
<artifact id="StructureDefinition/2.16.840.1.113883.10.20.22.4.505" key="StructureDefinition-2.16.840.1.113883.10.20.22.4.505" name="Disability Status Observation"/>
<artifact id="Binary/discharge-diagnosis-section-v3-example" key="Binary-discharge-diagnosis-section-v3-example" name="Discharge Diagnosis Example"/>
<artifact id="StructureDefinition/2.16.840.1.113883.10.20.22.2.24" key="StructureDefinition-2.16.840.1.113883.10.20.22.2.24" name="Discharge Diagnosis Section"/>
<artifact id="StructureDefinition/1.3.6.1.4.1.19376.1.5.3.1.3.33" key="StructureDefinition-1.3.6.1.4.1.19376.1.5.3.1.3.33" name="Discharge Diet Section (DEPRECATED)"/>
<artifact id="StructureDefinition/2.16.840.1.113883.10.20.22.4.35" key="StructureDefinition-2.16.840.1.113883.10.20.22.4.35" name="Discharge Medication"/>
<artifact id="Binary/discharge-medication-v3-example" key="Binary-discharge-medication-v3-example" name="Discharge Medication Example"/>
<artifact id="StructureDefinition/2.16.840.1.113883.10.20.22.2.11.1" key="StructureDefinition-2.16.840.1.113883.10.20.22.2.11.1" name="Discharge Medications Section"/>
<artifact id="Binary/discharge-medication-section-v3-example" key="Binary-discharge-medication-section-v3-example" name="Discharge Medications Section Example"/>
<artifact id="StructureDefinition/2.16.840.1.113883.10.20.22.1.8" key="StructureDefinition-2.16.840.1.113883.10.20.22.1.8" name="Discharge Summary"/>
<artifact id="Binary/discharge-summary-encompassingencounter-example" key="Binary-discharge-summary-encompassingencounter-example" name="Discharge Summary encompassingEncounter Example"/>
<artifact id="StructureDefinition/2.16.840.1.113883.10.20.22.4.308" key="StructureDefinition-2.16.840.1.113883.10.20.22.4.308" name="Distinct Identification Code Observation"/>
<artifact id="StructureDefinition/2.16.840.1.113883.10.20.22.4.123" key="StructureDefinition-2.16.840.1.113883.10.20.22.4.123" name="Drug Monitoring Act"/>
<artifact id="Binary/drug-monitoring-act-example" key="Binary-drug-monitoring-act-example" name="Drug Monitoring Act Example"/>
<artifact id="StructureDefinition/2.16.840.1.113883.10.20.22.4.24" key="StructureDefinition-2.16.840.1.113883.10.20.22.4.24" name="Drug Vehicle"/>
<artifact id="Binary/drug-vehicle-example" key="Binary-drug-vehicle-example" name="Drug Vehicle Example"/>
<artifact id="StructureDefinition/2.16.840.1.113883.10.20.22.4.49" key="StructureDefinition-2.16.840.1.113883.10.20.22.4.49" name="Encounter Activity"/>
<artifact id="Binary/encounter-activity-v3-example" key="Binary-encounter-activity-v3-example" name="Encounter Activity Example"/>
<artifact id="StructureDefinition/2.16.840.1.113883.10.20.22.4.80" key="StructureDefinition-2.16.840.1.113883.10.20.22.4.80" name="Encounter Diagnosis"/>
<artifact id="Binary/encounter-diagnosis-v3-example" key="Binary-encounter-diagnosis-v3-example" name="Encounter Diagnosis Example"/>
<artifact id="StructureDefinition/2.16.840.1.113883.10.20.22.2.22.1" key="StructureDefinition-2.16.840.1.113883.10.20.22.2.22.1" name="Encounters Section"/>
<artifact id="Binary/encounters-section-v3-example" key="Binary-encounters-section-v3-example" name="Encounters Section Example"/>
<artifact id="StructureDefinition/2.16.840.1.113883.10.20.22.4.122" key="StructureDefinition-2.16.840.1.113883.10.20.22.4.122" name="Entry Reference"/>
<artifact id="Binary/entry-reference-example" key="Binary-entry-reference-example" name="Entry Reference Example"/>
<artifact id="StructureDefinition/2.16.840.1.113883.10.20.15.3.1" key="StructureDefinition-2.16.840.1.113883.10.20.15.3.1" name="Estimated Date of Delivery"/>
<artifact id="Binary/estimated-date-of-delivery-example" key="Binary-estimated-date-of-delivery-example" name="Estimated Date of Delivery Example"/>
<artifact id="Binary/allergy-to-food-egg" key="Binary-allergy-to-food-egg" name="Example of Allergy Intolerance to Food Egg"/>
<artifact id="StructureDefinition/2.16.840.1.113883.10.20.22.4.309" key="StructureDefinition-2.16.840.1.113883.10.20.22.4.309" name="Expiration Date Observation"/>
<artifact id="StructureDefinition/2.16.840.1.113883.10.20.22.4.115" key="StructureDefinition-2.16.840.1.113883.10.20.22.4.115" name="External Document Reference"/>
<artifact id="Binary/external-document-reference-example" key="Binary-external-document-reference-example" name="External Document Reference Example"/>
<artifact id="StructureDefinition/2.16.840.1.113883.10.20.22.4.47" key="StructureDefinition-2.16.840.1.113883.10.20.22.4.47" name="Family History Death Observation"/>
<artifact id="Binary/family-history-death-observation-example" key="Binary-family-history-death-observation-example" name="Family History Death Observation Example"/>
<artifact id="StructureDefinition/2.16.840.1.113883.10.20.22.4.46" key="StructureDefinition-2.16.840.1.113883.10.20.22.4.46" name="Family History Observation"/>
<artifact id="Binary/family-history-observation-v3-example" key="Binary-family-history-observation-v3-example" name="Family History Observation Example"/>
<artifact id="StructureDefinition/2.16.840.1.113883.10.20.22.4.45" key="StructureDefinition-2.16.840.1.113883.10.20.22.4.45" name="Family History Organizer"/>
<artifact id="Binary/family-history-organizer-v3-example" key="Binary-family-history-organizer-v3-example" name="Family History Organizer Example"/>
<artifact id="StructureDefinition/2.16.840.1.113883.10.20.22.2.15" key="StructureDefinition-2.16.840.1.113883.10.20.22.2.15" name="Family History Section"/>
<artifact id="Binary/family-history-section-v3-example" key="Binary-family-history-section-v3-example" name="Family History Section Example"/>
<artifact id="StructureDefinition/2.16.840.1.113883.10.20.22.4.67" key="StructureDefinition-2.16.840.1.113883.10.20.22.4.67" name="Functional Status Observation"/>
<artifact id="Binary/functional-status-observation-v2-example" key="Binary-functional-status-observation-v2-example" name="Functional Status Observation Example"/>
<artifact id="StructureDefinition/2.16.840.1.113883.10.20.22.4.66" key="StructureDefinition-2.16.840.1.113883.10.20.22.4.66" name="Functional Status Organizer"/>
<artifact id="Binary/functional-status-organizer-v2-example" key="Binary-functional-status-organizer-v2-example" name="Functional Status Organizer Example"/>
<artifact id="StructureDefinition/2.16.840.1.113883.10.20.22.4.68" key="StructureDefinition-2.16.840.1.113883.10.20.22.4.68" name="Functional Status Problem Observation (DEPRECATED)"/>
<artifact id="StructureDefinition/2.16.840.1.113883.10.20.22.2.14" key="StructureDefinition-2.16.840.1.113883.10.20.22.2.14" name="Functional Status Section"/>
<artifact id="Binary/functional-status-section-v2-example" key="Binary-functional-status-section-v2-example" name="Functional Status Section Example"/>
<artifact id="StructureDefinition/2.16.840.1.113883.10.20.34.3.45" key="StructureDefinition-2.16.840.1.113883.10.20.34.3.45" name="Gender Identity Observation"/>
<artifact id="StructureDefinition/2.16.840.1.113883.10.20.2.5" key="StructureDefinition-2.16.840.1.113883.10.20.2.5" name="General Status Section"/>
<artifact id="Binary/general-status-section-example" key="Binary-general-status-section-example" name="General Status Section Example"/>
<artifact id="StructureDefinition/2.16.840.1.113883.10.20.22.4.121" key="StructureDefinition-2.16.840.1.113883.10.20.22.4.121" name="Goal Observation"/>
<artifact id="Binary/goal-observation-example" key="Binary-goal-observation-example" name="Goal Observation Example"/>
<artifact id="StructureDefinition/2.16.840.1.113883.10.20.22.2.60" key="StructureDefinition-2.16.840.1.113883.10.20.22.2.60" name="Goals Section"/>
<artifact id="Binary/goals-section-example" key="Binary-goals-section-example" name="Goals Section Example"/>
<artifact id="StructureDefinition/2.16.840.1.113883.10.20.22.4.141" key="StructureDefinition-2.16.840.1.113883.10.20.22.4.141" name="Handoff Communication Participants"/>
<artifact id="Binary/handoff-communication-example" key="Binary-handoff-communication-example" name="Handoff Communication Participants Example"/>
<artifact id="StructureDefinition/2.16.840.1.113883.10.20.22.4.132" key="StructureDefinition-2.16.840.1.113883.10.20.22.4.132" name="Health Concern Act (V3)"/>
<artifact id="Binary/health-concern-act-example" key="Binary-health-concern-act-example" name="Health Concern Act Example"/>
<artifact id="StructureDefinition/2.16.840.1.113883.10.20.22.2.58" key="StructureDefinition-2.16.840.1.113883.10.20.22.2.58" name="Health Concerns Section"/>
<artifact id="Binary/health-concerns-section-example" key="Binary-health-concerns-section-example" name="Health Concerns Section Example"/>
<artifact id="StructureDefinition/2.16.840.1.113883.10.20.22.2.61" key="StructureDefinition-2.16.840.1.113883.10.20.22.2.61" name="Health Status Evaluations and Outcomes Section"/>
<artifact id="Binary/health-status-evaluations-and-outcomes-section-example" key="Binary-health-status-evaluations-and-outcomes-section-example" name="Health Status Evaluations and Outcomes Section Example"/>
<artifact id="StructureDefinition/2.16.840.1.113883.10.20.22.4.5" key="StructureDefinition-2.16.840.1.113883.10.20.22.4.5" name="Health Status Observation"/>
<artifact id="Binary/health-status-observation-v2-example" key="Binary-health-status-observation-v2-example" name="Health Status Observation Example"/>
<artifact id="StructureDefinition/2.16.840.1.113883.10.20.22.4.77" key="StructureDefinition-2.16.840.1.113883.10.20.22.4.77" name="Highest Pressure Ulcer Stage"/>
<artifact id="Binary/highest-pressure-ulcer-stage-example" key="Binary-highest-pressure-ulcer-stage-example" name="Highest Pressure Ulcer Stage Example"/>
<artifact id="Binary/history-of-present-illness-section-example" key="Binary-history-of-present-illness-section-example" name="History Of Present Illness Example"/>
<artifact id="StructureDefinition/2.16.840.1.113883.10.20.22.1.3" key="StructureDefinition-2.16.840.1.113883.10.20.22.1.3" name="History and Physical"/>
<artifact id="Binary/handp-encompassingencounter-example" key="Binary-handp-encompassingencounter-example" name="History and Physical Encompassing Encounter Example"/>
<artifact id="StructureDefinition/1.3.6.1.4.1.19376.1.5.3.1.3.4" key="StructureDefinition-1.3.6.1.4.1.19376.1.5.3.1.3.4" name="History of Present Illness Section"/>
<artifact id="StructureDefinition/2.16.840.1.113883.10.20.22.4.34" key="StructureDefinition-2.16.840.1.113883.10.20.22.4.34" name="Hospital Admission Diagnosis"/>
<artifact id="Binary/hospital-admission-diagnosis-v3-example" key="Binary-hospital-admission-diagnosis-v3-example" name="Hospital Admission Diagnosis Example"/>
<artifact id="StructureDefinition/2.16.840.1.113883.10.20.22.2.42" key="StructureDefinition-2.16.840.1.113883.10.20.22.2.42" name="Hospital Consultations Section"/>
<artifact id="Binary/hospital-consultations-section-example" key="Binary-hospital-consultations-section-example" name="Hospital Consultations Section Example"/>
<artifact id="StructureDefinition/1.3.6.1.4.1.19376.1.5.3.1.3.5" key="StructureDefinition-1.3.6.1.4.1.19376.1.5.3.1.3.5" name="Hospital Course Section"/>
<artifact id="Binary/hospital-course-section-example" key="Binary-hospital-course-section-example" name="Hospital Course Section Example"/>
<artifact id="StructureDefinition/2.16.840.1.113883.10.20.22.4.33" key="StructureDefinition-2.16.840.1.113883.10.20.22.4.33" name="Hospital Discharge Diagnosis"/>
<artifact id="Binary/hospital-discharge-diagnosis-v3-example" key="Binary-hospital-discharge-diagnosis-v3-example" name="Hospital Discharge Diagnosis Example"/>
<artifact id="StructureDefinition/2.16.840.1.113883.10.20.22.2.41" key="StructureDefinition-2.16.840.1.113883.10.20.22.2.41" name="Hospital Discharge Instructions Section"/>
<artifact id="Binary/hospital-discharge-instructions-section-example" key="Binary-hospital-discharge-instructions-section-example" name="Hospital Discharge Instructions Section Example"/>
<artifact id="StructureDefinition/1.3.6.1.4.1.19376.1.5.3.1.3.26" key="StructureDefinition-1.3.6.1.4.1.19376.1.5.3.1.3.26" name="Hospital Discharge Physical Section"/>
<artifact id="Binary/hospital-discharge-physical-section-example" key="Binary-hospital-discharge-physical-section-example" name="Hospital Discharge Physical Section Example"/>
<artifact id="StructureDefinition/2.16.840.1.113883.10.20.22.2.16" key="StructureDefinition-2.16.840.1.113883.10.20.22.2.16" name="Hospital Discharge Studies Summary Section"/>
<artifact id="Binary/hospital-discharge-studies-summary-section-example" key="Binary-hospital-discharge-studies-summary-section-example" name="Hospital Discharge Studies Summary Section Example"/>
<artifact id="StructureDefinition/2.16.840.1.113883.10.20.22.4.52" key="StructureDefinition-2.16.840.1.113883.10.20.22.4.52" name="Immunization Activity"/>
<artifact id="Binary/immunization-activity-v3-example" key="Binary-immunization-activity-v3-example" name="Immunization Activity Example"/>
<artifact id="StructureDefinition/2.16.840.1.113883.10.20.22.4.54" key="StructureDefinition-2.16.840.1.113883.10.20.22.4.54" name="Immunization Medication Information"/>
<artifact id="Binary/immunization-medication-information-v2-example" key="Binary-immunization-medication-information-v2-example" name="Immunization Medication Information Example"/>
<artifact id="StructureDefinition/2.16.840.1.113883.10.20.22.4.53" key="StructureDefinition-2.16.840.1.113883.10.20.22.4.53" name="Immunization Refusal Reason"/>
<artifact id="Binary/immunization-refusal-reason-example" key="Binary-immunization-refusal-reason-example" name="Immunization Refusal Reason Example"/>
<artifact id="StructureDefinition/2.16.840.1.113883.10.20.22.2.2.1" key="StructureDefinition-2.16.840.1.113883.10.20.22.2.2.1" name="Immunizations Section"/>
<artifact id="Binary/immunizations-section-v3-example" key="Binary-immunizations-section-v3-example" name="Immunizations Section Example"/>
<artifact id="StructureDefinition/2.16.840.1.113883.10.20.22.4.305" key="StructureDefinition-2.16.840.1.113883.10.20.22.4.305" name="Implantable Device Status Observation"/>
<artifact id="StructureDefinition/2.16.840.1.113883.10.20.22.2.33" key="StructureDefinition-2.16.840.1.113883.10.20.22.2.33" name="Implants Section (DEPRECATED)"/>
<artifact id="StructureDefinition/2.16.840.1.113883.10.20.22.4.19" key="StructureDefinition-2.16.840.1.113883.10.20.22.4.19" name="Indication (V3)"/>
<artifact id="Binary/indication-v2-example" key="Binary-indication-v2-example" name="Indication Example"/>
<artifact id="StructureDefinition/2.16.840.1.113883.10.20.22.4.20" key="StructureDefinition-2.16.840.1.113883.10.20.22.4.20" name="Instruction"/>
<artifact id="Binary/instruction-v2-example" key="Binary-instruction-v2-example" name="Instruction Example"/>
<artifact id="StructureDefinition/2.16.840.1.113883.10.20.22.2.45" key="StructureDefinition-2.16.840.1.113883.10.20.22.2.45" name="Instructions Section"/>
<artifact id="Binary/instructions-section-v2-example" key="Binary-instructions-section-v2-example" name="Instructions Section Example"/>
<artifact id="StructureDefinition/2.16.840.1.113883.10.20.22.4.131" key="StructureDefinition-2.16.840.1.113883.10.20.22.4.131" name="Intervention Act"/>
<artifact id="Binary/intervention-act-moodcodeint-example" key="Binary-intervention-act-moodcodeint-example" name="Intervention Act Example"/>
<artifact id="StructureDefinition/2.16.840.1.113883.10.20.21.2.3" key="StructureDefinition-2.16.840.1.113883.10.20.21.2.3" name="Interventions Section"/>
<artifact id="Binary/interventions-section-v3-example" key="Binary-interventions-section-v3-example" name="Interventions Section Example"/>
<artifact id="StructureDefinition/2.16.840.1.113883.10.20.22.4.314" key="StructureDefinition-2.16.840.1.113883.10.20.22.4.314" name="Latex Safety Observation"/>
<artifact id="StructureDefinition/2.16.840.1.113883.10.20.22.4.114" key="StructureDefinition-2.16.840.1.113883.10.20.22.4.114" name="Longitudinal Care Wound Observation"/>
<artifact id="Binary/longitudinal-care-wound-observation-example" key="Binary-longitudinal-care-wound-observation-example" name="Longitudinal Care Wound Observation Example"/>
<artifact id="StructureDefinition/2.16.840.1.113883.10.20.22.4.315" key="StructureDefinition-2.16.840.1.113883.10.20.22.4.315" name="Lot or Batch Number Observation"/>
<artifact id="StructureDefinition/2.16.840.1.113883.10.20.22.4.318" key="StructureDefinition-2.16.840.1.113883.10.20.22.4.318" name="MRI Safety Observation"/>
<artifact id="StructureDefinition/2.16.840.1.113883.10.20.22.4.316" key="StructureDefinition-2.16.840.1.113883.10.20.22.4.316" name="Manufacturing Date Observation"/>
<artifact id="StructureDefinition/2.16.840.1.113883.10.20.22.2.39" key="StructureDefinition-2.16.840.1.113883.10.20.22.2.39" name="Medical (General) History Section"/>
<artifact id="StructureDefinition/2.16.840.1.113883.10.20.22.4.135" key="StructureDefinition-2.16.840.1.113883.10.20.22.4.135" name="Medical Equipment Organizer"/>
<artifact id="Binary/medical-equipment-organizer-example" key="Binary-medical-equipment-organizer-example" name="Medical Equipment Organizer Example"/>
<artifact id="StructureDefinition/2.16.840.1.113883.10.20.22.2.23" key="StructureDefinition-2.16.840.1.113883.10.20.22.2.23" name="Medical Equipment Section"/>
<artifact id="Binary/medical-equipment-section-v2-example" key="Binary-medical-equipment-section-v2-example" name="Medical Equipment Section Example"/>
<artifact id="StructureDefinition/2.16.840.1.113883.10.20.22.4.16" key="StructureDefinition-2.16.840.1.113883.10.20.22.4.16" name="Medication Activity"/>
<artifact id="Binary/medication-activity-v2-example" key="Binary-medication-activity-v2-example" name="Medication Activity Example"/>
<artifact id="StructureDefinition/2.16.840.1.113883.10.20.22.4.18" key="StructureDefinition-2.16.840.1.113883.10.20.22.4.18" name="Medication Dispense (V3)"/>
<artifact id="Binary/medication-dispense-v2-example" key="Binary-medication-dispense-v2-example" name="Medication Dispense Example"/>
<artifact id="StructureDefinition/2.16.840.1.113883.10.20.22.4.147" key="StructureDefinition-2.16.840.1.113883.10.20.22.4.147" name="Medication Free Text Sig"/>
<artifact id="Binary/medication-free-text-sig-example" key="Binary-medication-free-text-sig-example" name="Medication Free Text Sig Example"/>
<artifact id="StructureDefinition/2.16.840.1.113883.10.20.22.4.23" key="StructureDefinition-2.16.840.1.113883.10.20.22.4.23" name="Medication Information"/>
<artifact id="Binary/medication-information-v2-example" key="Binary-medication-information-v2-example" name="Medication Information Example"/>
<artifact id="StructureDefinition/2.16.840.1.113883.10.20.22.4.17" key="StructureDefinition-2.16.840.1.113883.10.20.22.4.17" name="Medication Supply Order"/>
<artifact id="Binary/medication-supply-order-v2-example" key="Binary-medication-supply-order-v2-example" name="Medication Supply Order Example"/>
<artifact id="StructureDefinition/2.16.840.1.113883.10.20.22.2.38" key="StructureDefinition-2.16.840.1.113883.10.20.22.2.38" name="Medications Administered Section"/>
<artifact id="Binary/medications-administered-section-v2-example" key="Binary-medications-administered-section-v2-example" name="Medications Administered Section Example"/>
<artifact id="StructureDefinition/2.16.840.1.113883.10.20.22.2.1.1" key="StructureDefinition-2.16.840.1.113883.10.20.22.2.1.1" name="Medications Section"/>
<artifact id="Binary/medications-section-v2-example" key="Binary-medications-section-v2-example" name="Medications Section Example"/>
<artifact id="StructureDefinition/2.16.840.1.113883.10.20.22.4.74" key="StructureDefinition-2.16.840.1.113883.10.20.22.4.74" name="Mental Status Observation"/>
<artifact id="StructureDefinition/2.16.840.1.113883.10.20.22.4.75" key="StructureDefinition-2.16.840.1.113883.10.20.22.4.75" name="Mental Status Organizer"/>
<artifact id="Binary/mental-status-observation-v3-example" key="Binary-mental-status-observation-v3-example" name="Mental Status Organizer Example"/>
<artifact id="Binary/mental-status-organizer-v3-example" key="Binary-mental-status-organizer-v3-example" name="Mental Status Organizer Example - V3"/>
<artifact id="StructureDefinition/2.16.840.1.113883.10.20.22.2.56" key="StructureDefinition-2.16.840.1.113883.10.20.22.2.56" name="Mental Status Section"/>
<artifact id="Binary/mental-status-section-example" key="Binary-mental-status-section-example" name="Mental Status Section Example"/>
<artifact id="StructureDefinition/2.16.840.1.113883.10.20.22.4.317" key="StructureDefinition-2.16.840.1.113883.10.20.22.4.317" name="Model Number Observation"/>
<artifact id="Binary/no-known-medications-example" key="Binary-no-known-medications-example" name="No Known Medications Example"/>
<artifact id="Binary/no-known-problems-section-example" key="Binary-no-known-problems-section-example" name="No Known Problem Section Example - entries optional"/>
<artifact id="StructureDefinition/2.16.840.1.113883.10.20.22.4.50" key="StructureDefinition-2.16.840.1.113883.10.20.22.4.50" name="Non-Medicinal Supply Activity"/>
<artifact id="Binary/non-medicinal-supply-activity-v2-example" key="Binary-non-medicinal-supply-activity-v2-example" name="Non-Medicinal Supply Activity Example"/>
<artifact id="StructureDefinition/2.16.840.1.113883.10.20.22.4.202" key="StructureDefinition-2.16.840.1.113883.10.20.22.4.202" name="Note Activity"/>
<artifact id="StructureDefinition/2.16.840.1.113883.10.20.22.2.65" key="StructureDefinition-2.16.840.1.113883.10.20.22.2.65" name="Notes Section"/>
<artifact id="StructureDefinition/2.16.840.1.113883.10.20.22.4.76" key="StructureDefinition-2.16.840.1.113883.10.20.22.4.76" name="Number of Pressure Ulcers Observation"/>
<artifact id="Binary/number-of-pressure-ulcers-observation-v3-example" key="Binary-number-of-pressure-ulcers-observation-v3-example" name="Number of Pressure Ulcers Observation Example"/>
<artifact id="StructureDefinition/2.16.840.1.113883.10.20.22.4.138" key="StructureDefinition-2.16.840.1.113883.10.20.22.4.138" name="Nutrition Assessment"/>
<artifact id="Binary/nutrition-assessment-example" key="Binary-nutrition-assessment-example" name="Nutrition Assessment Example"/>
<artifact id="StructureDefinition/2.16.840.1.113883.10.20.22.4.130" key="StructureDefinition-2.16.840.1.113883.10.20.22.4.130" name="Nutrition Recommendation"/>
<artifact id="Binary/nutrition-recommendation-example" key="Binary-nutrition-recommendation-example" name="Nutrition Recommendation Example"/>
<artifact id="StructureDefinition/2.16.840.1.113883.10.20.22.2.57" key="StructureDefinition-2.16.840.1.113883.10.20.22.2.57" name="Nutrition Section"/>
<artifact id="Binary/nutrition-section-example" key="Binary-nutrition-section-example" name="Nutrition Section Example"/>
<artifact id="StructureDefinition/2.16.840.1.113883.10.20.22.4.124" key="StructureDefinition-2.16.840.1.113883.10.20.22.4.124" name="Nutritional Status Observation"/>
<artifact id="Binary/nutritional-status-observation-example" key="Binary-nutritional-status-observation-example" name="Nutritional Status Observation Example"/>
<artifact id="StructureDefinition/2.16.840.1.113883.10.20.21.2.1" key="StructureDefinition-2.16.840.1.113883.10.20.21.2.1" name="Objective Section"/>
<artifact id="Binary/objective-section-example" key="Binary-objective-section-example" name="Objective Section Example"/>
<artifact id="StructureDefinition/2.16.840.1.113883.10.20.22.1.7" key="StructureDefinition-2.16.840.1.113883.10.20.22.1.7" name="Operative Note"/>
<artifact id="StructureDefinition/2.16.840.1.113883.10.20.7.12" key="StructureDefinition-2.16.840.1.113883.10.20.7.12" name="Operative Note Fluids Section"/>
<artifact id="Binary/operative-note-fluids-section-example" key="Binary-operative-note-fluids-section-example" name="Operative Note Fluids Section Example"/>
<artifact id="StructureDefinition/2.16.840.1.113883.10.20.7.14" key="StructureDefinition-2.16.840.1.113883.10.20.7.14" name="Operative Note Surgical Procedure Section"/>
<artifact id="Binary/operative-note-surgical-procedure-section-example" key="Binary-operative-note-surgical-procedure-section-example" name="Operative Note Surgical Procedure Section Example"/>
<artifact id="Binary/operative-note-performer-example" key="Binary-operative-note-performer-example" name="Operative Note performer Example"/>
<artifact id="Binary/operative-note-serviceevent-example" key="Binary-operative-note-serviceevent-example" name="Operative Note serviceEvent Example"/>
<artifact id="StructureDefinition/2.16.840.1.113883.10.20.22.4.144" key="StructureDefinition-2.16.840.1.113883.10.20.22.4.144" name="Outcome Observation"/>
<artifact id="Binary/outcome-observation-example" key="Binary-outcome-observation-example" name="Outcome Observation Example"/>
<artifact id="StructureDefinition/2.16.840.1.113883.10.20.22.2.20" key="StructureDefinition-2.16.840.1.113883.10.20.22.2.20" name="Past Medical History"/>
<artifact id="Binary/past-medical-history-v3-example" key="Binary-past-medical-history-v3-example" name="Past Medical History Example"/>
<artifact id="Binary/patient-generated-document-authenticator-example" key="Binary-patient-generated-document-authenticator-example" name="Patient Generated Document authenticator"/>
<artifact id="Binary/patient-generated-document-author-example" key="Binary-patient-generated-document-author-example" name="Patient Generated Document author"/>
<artifact id="Binary/patient-generated-document-author-device-example" key="Binary-patient-generated-document-author-device-example" name="Patient Generated Document author device Example"/>
<artifact id="Binary/patient-generated-document-custodian-example" key="Binary-patient-generated-document-custodian-example" name="Patient Generated Document custodian Example"/>
<artifact id="Binary/patient-generated-document-dataenterer-example" key="Binary-patient-generated-document-dataenterer-example" name="Patient Generated Document dataEnterer"/>
<artifact id="Binary/patient-generated-document-infulfillmentof-example" key="Binary-patient-generated-document-infulfillmentof-example" name="Patient Generated Document inFulfillmentOf Example"/>
<artifact id="Binary/patient-generated-document-informant-example-informant" key="Binary-patient-generated-document-informant-example-informant" name="Patient Generated Document informant Example informant"/>
<artifact id="Binary/patient-generated-document-informant-relent-example" key="Binary-patient-generated-document-informant-relent-example" name="Patient Generated Document informant RelEnt Example"/>
<artifact id="Binary/patient-generated-document-informationrecipient" key="Binary-patient-generated-document-informationrecipient" name="Patient Generated Document informationRecipient Example"/>
<artifact id="Binary/patient-generated-document-legalauthenticator-example" key="Binary-patient-generated-document-legalauthenticator-example" name="Patient Generated Document legalAuthenticator Example"/>
<artifact id="Binary/patient-generated-document-participant-example" key="Binary-patient-generated-document-participant-example" name="Patient Generated Document participant Example"/>
<artifact id="Binary/patient-generated-document-recordtarget-example" key="Binary-patient-generated-document-recordtarget-example" name="Patient Generated Document recordTarget"/>
<artifact id="StructureDefinition/2.16.840.1.113883.10.20.22.4.140" key="StructureDefinition-2.16.840.1.113883.10.20.22.4.140" name="Patient Referral Act"/>
<artifact id="Binary/patient-referral-act-example" key="Binary-patient-referral-act-example" name="Patient Referral Act Example"/>
<artifact id="StructureDefinition/2.16.840.1.113883.10.20.22.2.18" key="StructureDefinition-2.16.840.1.113883.10.20.22.2.18" name="Payers Section"/>
<artifact id="Binary/payers-section-v3-example" key="Binary-payers-section-v3-example" name="Payers Section Example"/>
<artifact id="StructureDefinition/2.16.840.1.113883.10.20.2.10" key="StructureDefinition-2.16.840.1.113883.10.20.2.10" name="Physical Exam Section"/>
<artifact id="Binary/physical-exam-section-v3-example" key="Binary-physical-exam-section-v3-example" name="Physical Exam Section Example"/>
<artifact id="StructureDefinition/2.16.840.1.113883.10.20.22.2.10" key="StructureDefinition-2.16.840.1.113883.10.20.22.2.10" name="Plan of Treatment Section"/>
<artifact id="Binary/plan-of-treatment-section-v2-example" key="Binary-plan-of-treatment-section-v2-example" name="Plan of Treatment Section Example"/>
<artifact id="StructureDefinition/2.16.840.1.113883.10.20.22.4.39" key="StructureDefinition-2.16.840.1.113883.10.20.22.4.39" name="Planned Act"/>
<artifact id="Binary/planned-act-v2-example" key="Binary-planned-act-v2-example" name="Planned Act Example"/>
<artifact id="StructureDefinition/2.16.840.1.113883.10.20.22.4.129" key="StructureDefinition-2.16.840.1.113883.10.20.22.4.129" name="Planned Coverage"/>
<artifact id="Binary/planned-coverage-example" key="Binary-planned-coverage-example" name="Planned Coverage Example"/>
<artifact id="StructureDefinition/2.16.840.1.113883.10.20.22.4.40" key="StructureDefinition-2.16.840.1.113883.10.20.22.4.40" name="Planned Encounter"/>
<artifact id="Binary/planned-encounter-v2-example" key="Binary-planned-encounter-v2-example" name="Planned Encounter Example"/>
<artifact id="StructureDefinition/2.16.840.1.113883.10.20.22.4.120" key="StructureDefinition-2.16.840.1.113883.10.20.22.4.120" name="Planned Immunization Activity"/>
<artifact id="Binary/planned-immunization-activity" key="Binary-planned-immunization-activity" name="Planned Immunization Activity Example"/>
<artifact id="StructureDefinition/2.16.840.1.113883.10.20.22.4.146" key="StructureDefinition-2.16.840.1.113883.10.20.22.4.146" name="Planned Intervention Act"/>
<artifact id="StructureDefinition/2.16.840.1.113883.10.20.22.4.42" key="StructureDefinition-2.16.840.1.113883.10.20.22.4.42" name="Planned Medication Activity"/>
<artifact id="Binary/planned-medication-activity-v2-example" key="Binary-planned-medication-activity-v2-example" name="Planned Medication Activity Example"/>
<artifact id="StructureDefinition/2.16.840.1.113883.10.20.22.4.44" key="StructureDefinition-2.16.840.1.113883.10.20.22.4.44" name="Planned Observation"/>
<artifact id="Binary/planned-observation-v2-example" key="Binary-planned-observation-v2-example" name="Planned Observation Example"/>
<artifact id="StructureDefinition/2.16.840.1.113883.10.20.22.4.41" key="StructureDefinition-2.16.840.1.113883.10.20.22.4.41" name="Planned Procedure (V3)"/>
<artifact id="Binary/planned-procedure-v2-example" key="Binary-planned-procedure-v2-example" name="Planned Procedure Example"/>
<artifact id="StructureDefinition/2.16.840.1.113883.10.20.22.2.30" key="StructureDefinition-2.16.840.1.113883.10.20.22.2.30" name="Planned Procedure Section"/>
<artifact id="Binary/planned-procedure-section-v2-example" key="Binary-planned-procedure-section-v2-example" name="Planned Procedure Section Example"/>
<artifact id="StructureDefinition/2.16.840.1.113883.10.20.22.4.43" key="StructureDefinition-2.16.840.1.113883.10.20.22.4.43" name="Planned Supply"/>
<artifact id="Binary/planned-supply-v2-example" key="Binary-planned-supply-v2-example" name="Planned Supply Example"/>
<artifact id="StructureDefinition/2.16.840.1.113883.10.20.22.4.61" key="StructureDefinition-2.16.840.1.113883.10.20.22.4.61" name="Policy Activity"/>
<artifact id="Binary/policy-activity-v3-example" key="Binary-policy-activity-v3-example" name="Policy Activity Example"/>
<artifact id="StructureDefinition/2.16.840.1.113883.10.20.22.2.35" key="StructureDefinition-2.16.840.1.113883.10.20.22.2.35" name="Postoperative Diagnosis Section"/>
<artifact id="Binary/postoperative-diagnosis-section-example" key="Binary-postoperative-diagnosis-section-example" name="Postoperative Diagnosis Section Example"/>
<artifact id="StructureDefinition/2.16.840.1.113883.10.20.22.4.51" key="StructureDefinition-2.16.840.1.113883.10.20.22.4.51" name="Postprocedure Diagnosis"/>
<artifact id="Binary/postprocedure-diagnosis-v3-example" key="Binary-postprocedure-diagnosis-v3-example" name="Postprocedure Diagnosis Example"/>
<artifact id="StructureDefinition/2.16.840.1.113883.10.20.22.2.36" key="StructureDefinition-2.16.840.1.113883.10.20.22.2.36" name="Postprocedure Diagnosis Section"/>
<artifact id="Binary/postprocedure-diagnosis-section-v3-example" key="Binary-postprocedure-diagnosis-section-v3-example" name="Postprocedure Diagnosis Section Example"/>
<artifact id="StructureDefinition/2.16.840.1.113883.10.20.22.4.25" key="StructureDefinition-2.16.840.1.113883.10.20.22.4.25" name="Precondition for Substance Administration"/>
<artifact id="Binary/precondition-for-substance-administration-v2-example" key="Binary-precondition-for-substance-administration-v2-example" name="Precondition for Substance Administration Example"/>
<artifact id="StructureDefinition/2.16.840.1.113883.10.20.22.4.281" key="StructureDefinition-2.16.840.1.113883.10.20.22.4.281" name="Pregnancy Intention in Next Year"/>
<artifact id="StructureDefinition/2.16.840.1.113883.10.20.15.3.8" key="StructureDefinition-2.16.840.1.113883.10.20.15.3.8" name="Pregnancy Observation"/>
<artifact id="Binary/pregnancy-observation-example" key="Binary-pregnancy-observation-example" name="Pregnancy Observation Example"/>
<artifact id="StructureDefinition/2.16.840.1.113883.10.20.22.4.65" key="StructureDefinition-2.16.840.1.113883.10.20.22.4.65" name="Preoperative Diagnosis"/>
<artifact id="Binary/preoperative-diagnosis-v3-example" key="Binary-preoperative-diagnosis-v3-example" name="Preoperative Diagnosis Example"/>
<artifact id="StructureDefinition/2.16.840.1.113883.10.20.22.2.34" key="StructureDefinition-2.16.840.1.113883.10.20.22.2.34" name="Preoperative Diagnosis Section"/>
<artifact id="Binary/preoperative-diagnosis-section-v3-example" key="Binary-preoperative-diagnosis-section-v3-example" name="Preoperative Diagnosis Section Example"/>
<artifact id="StructureDefinition/2.16.840.1.113883.10.20.22.4.70" key="StructureDefinition-2.16.840.1.113883.10.20.22.4.70" name="Pressure Ulcer Observation (DEPRECATED)"/>
<artifact id="StructureDefinition/2.16.840.1.113883.10.20.22.4.143" key="StructureDefinition-2.16.840.1.113883.10.20.22.4.143" name="Priority Preference"/>
<artifact id="Binary/priority-preference-example" key="Binary-priority-preference-example" name="Priority Preference Example"/>
<artifact id="StructureDefinition/2.16.840.1.113883.10.20.22.4.3" key="StructureDefinition-2.16.840.1.113883.10.20.22.4.3" name="Problem Concern Act"/>
<artifact id="Binary/problem-concern-act-v3-example" key="Binary-problem-concern-act-v3-example" name="Problem Concern Act Example"/>
<artifact id="StructureDefinition/2.16.840.1.113883.10.20.22.4.4" key="StructureDefinition-2.16.840.1.113883.10.20.22.4.4" name="Problem Observation"/>
<artifact id="Binary/problem-observation-v3-example" key="Binary-problem-observation-v3-example" name="Problem Observation Example"/>
<artifact id="StructureDefinition/2.16.840.1.113883.10.20.22.2.5.1" key="StructureDefinition-2.16.840.1.113883.10.20.22.2.5.1" name="Problem Section"/>
<artifact id="Binary/problem-section-v3-example" key="Binary-problem-section-v3-example" name="Problem Section Example"/>
<artifact id="StructureDefinition/2.16.840.1.113883.10.20.22.4.6" key="StructureDefinition-2.16.840.1.113883.10.20.22.4.6" name="Problem Status"/>
<artifact id="StructureDefinition/2.16.840.1.113883.10.20.22.4.12" key="StructureDefinition-2.16.840.1.113883.10.20.22.4.12" name="Procedure Activity Act"/>
<artifact id="Binary/procedure-activity-act-example" key="Binary-procedure-activity-act-example" name="Procedure Activity Act Example"/>
<artifact id="StructureDefinition/2.16.840.1.113883.10.20.22.4.13" key="StructureDefinition-2.16.840.1.113883.10.20.22.4.13" name="Procedure Activity Observation"/>
<artifact id="Binary/procedure-activity-observation-v2-example" key="Binary-procedure-activity-observation-v2-example" name="Procedure Activity Observation Example"/>
<artifact id="StructureDefinition/2.16.840.1.113883.10.20.22.4.14" key="StructureDefinition-2.16.840.1.113883.10.20.22.4.14" name="Procedure Activity Procedure (V3)"/>
<artifact id="Binary/procedure-activity-procedure-v2-example" key="Binary-procedure-activity-procedure-v2-example" name="Procedure Activity Procedure Example"/>
<artifact id="Binary/procedure-context-example" key="Binary-procedure-context-example" name="Procedure Content"/>
<artifact id="StructureDefinition/2.16.840.1.113883.10.20.22.2.27" key="StructureDefinition-2.16.840.1.113883.10.20.22.2.27" name="Procedure Description Section"/>
<artifact id="Binary/procedure-description-section-example" key="Binary-procedure-description-section-example" name="Procedure Description Section Example"/>
<artifact id="StructureDefinition/2.16.840.1.113883.10.20.18.2.12" key="StructureDefinition-2.16.840.1.113883.10.20.18.2.12" name="Procedure Disposition Section"/>
<artifact id="Binary/procedure-disposition-section-example" key="Binary-procedure-disposition-section-example" name="Procedure Disposition Section Example"/>
<artifact id="StructureDefinition/2.16.840.1.113883.10.20.18.2.9" key="StructureDefinition-2.16.840.1.113883.10.20.18.2.9" name="Procedure Estimated Blood Loss Section"/>
<artifact id="Binary/procedure-estimated-blood-loss-section-example" key="Binary-procedure-estimated-blood-loss-section-example" name="Procedure Estimated Blood Loss Section Example"/>
<artifact id="StructureDefinition/2.16.840.1.113883.10.20.22.2.28" key="StructureDefinition-2.16.840.1.113883.10.20.22.2.28" name="Procedure Findings Section"/>
<artifact id="Binary/procedure-findings-section-v3-example" key="Binary-procedure-findings-section-v3-example" name="Procedure Findings Section Example"/>
<artifact id="StructureDefinition/2.16.840.1.113883.10.20.22.2.40" key="StructureDefinition-2.16.840.1.113883.10.20.22.2.40" name="Procedure Implants Section"/>
<artifact id="Binary/procedure-implants-section-example" key="Binary-procedure-implants-section-example" name="Procedure Implants Section Example"/>
<artifact id="StructureDefinition/2.16.840.1.113883.10.20.22.2.29" key="StructureDefinition-2.16.840.1.113883.10.20.22.2.29" name="Procedure Indications Section"/>
<artifact id="Binary/procedure-indications-section-v2-example" key="Binary-procedure-indications-section-v2-example" name="Procedure Indications Section Example"/>
<artifact id="StructureDefinition/2.16.840.1.113883.10.20.22.1.6" key="StructureDefinition-2.16.840.1.113883.10.20.22.1.6" name="Procedure Note"/>
<artifact id="Binary/procedure-note-performer-example" key="Binary-procedure-note-performer-example" name="Procedure Note performer Example"/>
<artifact id="Binary/procedure-note-serviceevent-example" key="Binary-procedure-note-serviceevent-example" name="Procedure Note serviceEvent Example"/>
<artifact id="StructureDefinition/2.16.840.1.113883.10.20.22.2.31" key="StructureDefinition-2.16.840.1.113883.10.20.22.2.31" name="Procedure Specimens Taken Section"/>
<artifact id="Binary/procedure-specimens-taken-section-example" key="Binary-procedure-specimens-taken-section-example" name="Procedure Specimens Taken Section Example"/>
<artifact id="StructureDefinition/2.16.840.1.113883.10.20.22.2.7.1" key="StructureDefinition-2.16.840.1.113883.10.20.22.2.7.1" name="Procedures Section"/>
<artifact id="Binary/procedures-section-v2-example" key="Binary-procedures-section-v2-example" name="Procedures Section Example"/>
<artifact id="StructureDefinition/2.16.840.1.113883.10.20.22.4.37" key="StructureDefinition-2.16.840.1.113883.10.20.22.4.37" name="Product Instance"/>
<artifact id="Binary/product-instance-example" key="Binary-product-instance-example" name="Product Instance Example"/>
<artifact id="Binary/prognosis-coded-example" key="Binary-prognosis-coded-example" name="Prognosis Coded Example"/>
<artifact id="Binary/prognosis-free-text-example" key="Binary-prognosis-free-text-example" name="Prognosis Free Text Example"/>
<artifact id="StructureDefinition/2.16.840.1.113883.10.20.22.4.113" key="StructureDefinition-2.16.840.1.113883.10.20.22.4.113" name="Prognosis Observation"/>
<artifact id="StructureDefinition/2.16.840.1.113883.10.20.22.1.9" key="StructureDefinition-2.16.840.1.113883.10.20.22.1.9" name="Progress Note"/>
<artifact id="Binary/progress-note-encompassingencounter-example" key="Binary-progress-note-encompassingencounter-example" name="Progress Note encompassingEncounter Example"/>
<artifact id="Binary/progress-note-serviceevent-example" key="Binary-progress-note-serviceevent-example" name="Progress Note serviceEvent Example"/>
<artifact id="StructureDefinition/2.16.840.1.113883.10.20.22.4.110" key="StructureDefinition-2.16.840.1.113883.10.20.22.4.110" name="Progress Toward Goal Observation"/>
<artifact id="Binary/progress-toward-goal-observation-example" key="Binary-progress-toward-goal-observation-example" name="Progress Toward Goal Observation Example"/>
<artifact id="StructureDefinition/2.16.840.1.113883.10.20.22.5.7" key="StructureDefinition-2.16.840.1.113883.10.20.22.5.7" name="Provenance - Assembler Participation"/>
<artifact id="StructureDefinition/2.16.840.1.113883.10.20.22.5.6" key="StructureDefinition-2.16.840.1.113883.10.20.22.5.6" name="Provenance - Author Participation"/>
<artifact id="StructureDefinition/2.16.840.1.113883.10.20.22.4.9" key="StructureDefinition-2.16.840.1.113883.10.20.22.4.9" name="Reaction Observation"/>
<artifact id="Binary/reaction-observation-v2-example" key="Binary-reaction-observation-v2-example" name="Reaction Observation Example"/>
<artifact id="StructureDefinition/2.16.840.1.113883.10.20.24.3.88" key="StructureDefinition-2.16.840.1.113883.10.20.24.3.88" name="Reason"/>
<artifact id="Binary/reason-for-referral-section-v2-example" key="Binary-reason-for-referral-section-v2-example" name="Reason For Referral"/>
<artifact id="StructureDefinition/1.3.6.1.4.1.19376.1.5.3.1.3.1" key="StructureDefinition-1.3.6.1.4.1.19376.1.5.3.1.3.1" name="Reason for Referral Section"/>
<artifact id="StructureDefinition/2.16.840.1.113883.10.20.22.2.12" key="StructureDefinition-2.16.840.1.113883.10.20.22.2.12" name="Reason for Visit Section"/>
<artifact id="Binary/reason-for-visit-section-example" key="Binary-reason-for-visit-section-example" name="Reason for Visit Section Example"/>
<artifact id="StructureDefinition/2.16.840.1.113883.10.20.22.1.14" key="StructureDefinition-2.16.840.1.113883.10.20.22.1.14" name="Referral Note"/>
<artifact id="Binary/referral-note-callback-contact-example" key="Binary-referral-note-callback-contact-example" name="Referral Note Callback Contact Example"/>
<artifact id="Binary/referral-note-caregiver-example" key="Binary-referral-note-caregiver-example" name="Referral Note Caregiver"/>
<artifact id="Binary/referral-note-informationrecipient-example" key="Binary-referral-note-informationrecipient-example" name="Referral Note informationRecipient Example"/>
<artifact id="StructureDefinition/2.16.840.1.113883.10.20.22.5.8" key="StructureDefinition-2.16.840.1.113883.10.20.22.5.8" name="Related Person Relationship and Name Participant"/>
<artifact id="StructureDefinition/2.16.840.1.113883.10.20.22.4.2" key="StructureDefinition-2.16.840.1.113883.10.20.22.4.2" name="Result Observation"/>
<artifact id="Binary/result-observation-v3-example" key="Binary-result-observation-v3-example" name="Result Observation Example"/>
<artifact id="StructureDefinition/2.16.840.1.113883.10.20.22.4.1" key="StructureDefinition-2.16.840.1.113883.10.20.22.4.1" name="Result Organizer"/>
<artifact id="Binary/result-organizer-v3-example" key="Binary-result-organizer-v3-example" name="Result Organizer Example"/>
<artifact id="StructureDefinition/2.16.840.1.113883.10.20.22.2.3.1" key="StructureDefinition-2.16.840.1.113883.10.20.22.2.3.1" name="Results Section"/>
<artifact id="Binary/results-section-v3-example" key="Binary-results-section-v3-example" name="Results Section Example"/>
<artifact id="Binary/review-of-systems-section-example" key="Binary-review-of-systems-section-example" name="Review Of Systems Section Example"/>
<artifact id="StructureDefinition/1.3.6.1.4.1.19376.1.5.3.1.3.18" key="StructureDefinition-1.3.6.1.4.1.19376.1.5.3.1.3.18" name="Review of Systems Section"/>
<artifact id="StructureDefinition/2.16.840.1.113883.10.20.22.4.136" key="StructureDefinition-2.16.840.1.113883.10.20.22.4.136" name="Risk Concern Act"/>
<artifact id="Binary/risk-concern-act-example" key="Binary-risk-concern-act-example" name="Risk Concern Act Example"/>
<artifact id="StructureDefinition/2.16.840.1.113883.10.20.22.4.201" key="StructureDefinition-2.16.840.1.113883.10.20.22.4.201" name="Section Time Range Observation"/>
<artifact id="StructureDefinition/2.16.840.1.113883.10.20.22.4.128" key="StructureDefinition-2.16.840.1.113883.10.20.22.4.128" name="Self-Care Activities (ADL and IADL)"/>
<artifact id="Binary/self-care-activities-adl-and-iadl-example" key="Binary-self-care-activities-adl-and-iadl-example" name="Self-Care Activities ADL and IADL Example"/>
<artifact id="StructureDefinition/2.16.840.1.113883.10.20.22.4.127" key="StructureDefinition-2.16.840.1.113883.10.20.22.4.127" name="Sensory Status"/>
<artifact id="Binary/sensory-and-speech-status-example" key="Binary-sensory-and-speech-status-example" name="Sensory Status Example"/>
<artifact id="StructureDefinition/2.16.840.1.113883.10.20.22.4.319" key="StructureDefinition-2.16.840.1.113883.10.20.22.4.319" name="Serial Number Observation"/>
<artifact id="StructureDefinition/2.16.840.1.113883.10.20.22.4.32" key="StructureDefinition-2.16.840.1.113883.10.20.22.4.32" name="Service Delivery Location"/>
<artifact id="Binary/service-delivery-location-example" key="Binary-service-delivery-location-example" name="Service Delivery Location Example"/>
<artifact id="StructureDefinition/2.16.840.1.113883.10.20.22.4.8" key="StructureDefinition-2.16.840.1.113883.10.20.22.4.8" name="Severity Observation"/>
<artifact id="Binary/severity-observation-v2-example" key="Binary-severity-observation-v2-example" name="Severity Observation Example"/>
<artifact id="StructureDefinition/2.16.840.1.113883.10.20.22.4.507" key="StructureDefinition-2.16.840.1.113883.10.20.22.4.507" name="Sex Observation"/>
<artifact id="StructureDefinition/2.16.840.1.113883.10.20.22.4.501" key="StructureDefinition-2.16.840.1.113883.10.20.22.4.501" name="Sexual Orientation Observation"/>
<artifact id="StructureDefinition/2.16.840.1.113883.10.20.22.4.78" key="StructureDefinition-2.16.840.1.113883.10.20.22.4.78" name="Smoking Status - Meaningful Use"/>
<artifact id="Binary/smoking-status-meaningful-use-v2-example" key="Binary-smoking-status-meaningful-use-v2-example" name="Smoking Status Meaningful Use Example"/>
<artifact id="StructureDefinition/2.16.840.1.113883.10.20.22.4.38" key="StructureDefinition-2.16.840.1.113883.10.20.22.4.38" name="Social History Observation"/>
<artifact id="Binary/social-history-observation-v3-example" key="Binary-social-history-observation-v3-example" name="Social History Observation Example"/>
<artifact id="StructureDefinition/2.16.840.1.113883.10.20.22.2.17" key="StructureDefinition-2.16.840.1.113883.10.20.22.2.17" name="Social History Section"/>
<artifact id="Binary/social-history-section-v3-example" key="Binary-social-history-section-v3-example" name="Social History Section Example"/>
<artifact id="StructureDefinition/2.16.840.1.113883.10.20.21.2.2" key="StructureDefinition-2.16.840.1.113883.10.20.21.2.2" name="Subjective Section"/>
<artifact id="Binary/subjective-section-example" key="Binary-subjective-section-example" name="Subjective Section Example"/>
<artifact id="StructureDefinition/2.16.840.1.113883.10.20.22.4.118" key="StructureDefinition-2.16.840.1.113883.10.20.22.4.118" name="Substance Administered Act"/>
<artifact id="Binary/substance-administered-act-example" key="Binary-substance-administered-act-example" name="Substance Administered Act Example"/>
<artifact id="StructureDefinition/2.16.840.1.113883.10.20.24.3.90" key="StructureDefinition-2.16.840.1.113883.10.20.24.3.90" name="Substance or Device Allergy - Intolerance Observation"/>
<artifact id="StructureDefinition/2.16.840.1.113883.10.20.22.2.26" key="StructureDefinition-2.16.840.1.113883.10.20.22.2.26" name="Surgery Description Section (DEPRECATED)"/>
<artifact id="StructureDefinition/2.16.840.1.113883.10.20.7.13" key="StructureDefinition-2.16.840.1.113883.10.20.7.13" name="Surgical Drains Section"/>
<artifact id="Binary/surgical-drains-section-example" key="Binary-surgical-drains-section-example" name="Surgical Drains Section Example"/>
<artifact id="StructureDefinition/2.16.840.1.113883.10.20.22.4.85" key="StructureDefinition-2.16.840.1.113883.10.20.22.4.85" name="Tobacco Use"/>
<artifact id="Binary/tobacco-use-v2-example" key="Binary-tobacco-use-v2-example" name="Tobacco Use Example"/>
<artifact id="StructureDefinition/2.16.840.1.113883.10.20.22.1.13" key="StructureDefinition-2.16.840.1.113883.10.20.22.1.13" name="Transfer Summary"/>
<artifact id="Binary/transfer-summary-callback-contact-example" key="Binary-transfer-summary-callback-contact-example" name="Transfer Summary Callback Contact Example"/>
<artifact id="Binary/transfer-summary-participant-support-example" key="Binary-transfer-summary-participant-support-example" name="Transfer Summary participant (Support) Example"/>
<artifact id="StructureDefinition/2.16.840.1.113883.10.20.22.4.506" key="StructureDefinition-2.16.840.1.113883.10.20.22.4.506" name="Tribal Affiliation Observation"/>
<artifact id="StructureDefinition/2.16.840.1.113883.10.20.22.4.311" key="StructureDefinition-2.16.840.1.113883.10.20.22.4.311" name="UDI Organizer"/>
<artifact id="StructureDefinition/2.16.840.1.113883.10.20.22.5.2" key="StructureDefinition-2.16.840.1.113883.10.20.22.5.2" name="US Realm Address (AD.US.FIELDED)"/>
<artifact id="Binary/us-realm-address-example" key="Binary-us-realm-address-example" name="US Realm Address Example"/>
<artifact id="StructureDefinition/2.16.840.1.113883.10.20.22.5.3" key="StructureDefinition-2.16.840.1.113883.10.20.22.5.3" name="US Realm Date and Time (DT.US.FIELDED)"/>
<artifact id="StructureDefinition/2.16.840.1.113883.10.20.22.5.4" key="StructureDefinition-2.16.840.1.113883.10.20.22.5.4" name="US Realm Date and Time (DTM.US.FIELDED)"/>
<artifact id="Binary/us-realm-date-and-time-example" key="Binary-us-realm-date-and-time-example" name="US Realm Date and Time Example"/>
<artifact id="StructureDefinition/2.16.840.1.113883.10.20.22.1.1" key="StructureDefinition-2.16.840.1.113883.10.20.22.1.1" name="US Realm Header"/>
<artifact id="Binary/us-realm-header-v3-example" key="Binary-us-realm-header-v3-example" name="US Realm Header Example"/>
<artifact id="StructureDefinition/2.16.840.1.113883.10.20.29.1" key="StructureDefinition-2.16.840.1.113883.10.20.29.1" name="US Realm Header for Patient Generated Document"/>
<artifact id="StructureDefinition/2.16.840.1.113883.10.20.22.5.1" key="StructureDefinition-2.16.840.1.113883.10.20.22.5.1" name="US Realm Patient Name (PTN.US.FIELDED)"/>
<artifact id="Binary/us-realm-patient-name-example" key="Binary-us-realm-patient-name-example" name="US Realm Patient Name Example"/>
<artifact id="StructureDefinition/2.16.840.1.113883.10.20.22.5.1.1" key="StructureDefinition-2.16.840.1.113883.10.20.22.5.1.1" name="US Realm Person Name (PN.US.FIELDED)"/>
<artifact id="Binary/us-realm-person-name-example" key="Binary-us-realm-person-name-example" name="US Realm Person Name Example"/>
<artifact id="StructureDefinition/2.16.840.1.113883.10.20.22.1.10" key="StructureDefinition-2.16.840.1.113883.10.20.22.1.10" name="Unstructured Document"/>
<artifact id="StructureDefinition/2.16.840.1.113883.10.20.22.4.27" key="StructureDefinition-2.16.840.1.113883.10.20.22.4.27" name="Vital Sign Observation"/>
<artifact id="Binary/vital-sign-observation-v2-example" key="Binary-vital-sign-observation-v2-example" name="Vital Sign Observation Example"/>
<artifact id="StructureDefinition/2.16.840.1.113883.10.20.22.4.26" key="StructureDefinition-2.16.840.1.113883.10.20.22.4.26" name="Vital Signs Organizer"/>
<artifact id="Binary/vital-signs-organizer-v3-example" key="Binary-vital-signs-organizer-v3-example" name="Vital Signs Organizer Example"/>
<artifact id="StructureDefinition/2.16.840.1.113883.10.20.22.2.4.1" key="StructureDefinition-2.16.840.1.113883.10.20.22.2.4.1" name="Vital Signs Section"/>
<artifact id="Binary/vital-signs-section-v3-example" key="Binary-vital-signs-section-v3-example" name="Vital Signs Section Example"/>
<artifact id="StructureDefinition/2.16.840.1.113883.10.20.22.4.134" key="StructureDefinition-2.16.840.1.113883.10.20.22.4.134" name="Wound Characteristic"/>
<artifact id="Binary/wound-characteristic-example" key="Binary-wound-characteristic-example" name="Wound Characteristic Example"/>
<artifact id="StructureDefinition/2.16.840.1.113883.10.20.22.4.133" key="StructureDefinition-2.16.840.1.113883.10.20.22.4.133" name="Wound Measurement Observation"/>
<artifact id="Binary/wound-measurement-observation-example" key="Binary-wound-measurement-observation-example" name="Wound Measurement Observation Example"/>
<artifact id="Binary/nonxmlbody-example-with-compressed-content" key="Binary-nonxmlbody-example-with-compressed-content" name="nonXML Body Example with Compressed Content"/>
<artifact id="Binary/nonxmlbody-example-with-embedded-content" key="Binary-nonxmlbody-example-with-embedded-content" name="nonXML Body Example with Embedded Content"/>
<artifact id="Binary/nonxmlbody-example-with-referenced-content" key="Binary-nonxmlbody-example-with-referenced-content" name="nonXML Body Example with Referenced Content"/>
<page key="NA" name="(NA)"/>
<page key="many" name="(many)"/>
<page key="appendix" name="Appendix"/>
<page key="artifacts" name="Artifacts Summary"/>
<page key="background" name="Background"/>
<page key="designconsiderations" name="Design Considerations"/>
<page key="document_level_guidance" name="Document Level Guidance"/>
<page key="downloads" name="Downloads"/>
<page key="howtoread" name="How To Read"/>
<page key="index" name="IG Home Page"/>
<page key="introduction" name="Introduction"/>
<page key="references" name="References"/>
<page key="representation_of_discrete_data" name="Representation of Discrete Data"/>
<page key="resources" name="Resources"/>
<page key="section_level_guidance" name="Section Level Guidance"/>
<page key="toc" name="Table of Contents"/>
<page key="uscdi_guidance" name="USCDI Guidance"/>
<page key="understanding_c-cda_and_the_c-cda_companion_guide" name="Understanding C-CDA and the C-CDA Companion Guide"/>
<page key="using" name="Using this Implementation Guide"/>
<page key="validation" name="Validation"/>
</specification>